img2sh/__init__.py
img2sh/cli.py
img2sh/pallette.py
img2sh/rect.py
img2sh/renderer.py
img2sh-0.2.2.dist-info/LICENSE
img2sh-0.2.2.dist-info/METADATA
img2sh-0.2.2.dist-info/WHEEL
img2sh-0.2.2.dist-info/entry_points.txt
img2sh-0.2.2.dist-info/top_level.txt
img2sh-0.2.2.dist-info/RECORD
