Metadata-Version: 2.1
Name: img2sh
Version: 0.2.2
Summary: Show images directly on terminal using Xterm colors.
Home-page: https://github.com/mozanunal/img2sh
Author: Mehmet Ozan Unal
Author-email: mehmetozanunal@gmail.com
Maintainer: Mehmet Ozan Unal
Maintainer-email: mehmetozanunal@gmail.com
License: MIT
Platform: all
Classifier: Development Status :: 4 - Beta
Classifier: Operating System :: OS Independent
Classifier: Intended Audience :: Developers
Classifier: License :: OSI Approved :: BSD License
Classifier: Programming Language :: Python
Classifier: Programming Language :: Python :: Implementation
Classifier: Programming Language :: Python :: 2
Classifier: Programming Language :: Python :: 2.7
Classifier: Programming Language :: Python :: 3
Classifier: Programming Language :: Python :: 3.4
Classifier: Programming Language :: Python :: 3.5
Classifier: Programming Language :: Python :: 3.6
Classifier: Programming Language :: Python :: 3.7
Classifier: Topic :: Software Development :: Libraries
License-File: LICENSE
Requires-Dist: colored
Requires-Dist: Pillow
Requires-Dist: six
Requires-Dist: numpy
